commit_text_organizer/__init__.py
commit_text_organizer/__main__.py
commit_text_organizer/argument_data.py
commit_text_organizer/argument_parser.py
commit_text_organizer/commit_line.py
commit_text_organizer/commit_line_group.py
commit_text_organizer/commit_line_prefixes.py
commit_text_organizer/commit_organizer.py
commit_text_organizer/file_validation.py
commit_text_organizer/input_data.py
tests/cto_samples/__init__.py
tests/cto_samples/assertions.py
tests/cto_samples/test_basic.py
tests/cto_samples/test_challenges.py
tests/cto_samples/test_generation.py
tests/cto_samples/test_git_log_filters.py
tests/cto_samples/test_pull_request.py
commit_text_organizer-1.1.2.dist-info/LICENSE
commit_text_organizer-1.1.2.dist-info/METADATA
commit_text_organizer-1.1.2.dist-info/WHEEL
commit_text_organizer-1.1.2.dist-info/entry_points.txt
commit_text_organizer-1.1.2.dist-info/top_level.txt
commit_text_organizer-1.1.2.dist-info/RECORD
