Metadata-Version: 2.1
Name: commit-text-organizer
Version: 1.1.2
Summary: A Text Processor Targeted at Organizing Commit Messages.
Home-page: https://github.com/DK96-OS/cto
Author: DK96-OS
License: GPLv3
Project-URL: Issues, https://github.com/DK96-OS/cto/issues
Project-URL: Source Code, https://github.com/DK96-OS/cto
Classifier: Natural Language :: English
Classifier: Operating System :: OS Independent
Classifier: Intended Audience :: Developers
Classifier: License :: OSI Approved :: GNU General Public License v3 (GPLv3)
Classifier: Programming Language :: Python :: 3
Classifier: Programming Language :: Python :: 3.10
Classifier: Programming Language :: Python :: 3.11
Classifier: Programming Language :: Python :: 3.12
Classifier: Programming Language :: Python :: 3.13
Requires-Python: >=3.10
License-File: LICENSE
